whyslow/__init__.py
whyslow/__main__.py
whyslow/profile.py
whyslow/term_process.py
whyslow/utils.py
whyslow-0.1.7.dist-info/LICENSE
whyslow-0.1.7.dist-info/METADATA
whyslow-0.1.7.dist-info/WHEEL
whyslow-0.1.7.dist-info/top_level.txt
whyslow-0.1.7.dist-info/RECORD
