Metadata-Version: 2.1
Name: whyslow
Version: 0.1.7
Summary: Developer-friendly performance profiling utility for Python
Author: valentinstn
Project-URL: GitHub, https://github.com/valentinstn/whyslow
Requires-Python: >=3.6
License-File: LICENSE
Requires-Dist: snakeviz
